{
  "year": 2024,
  "total_loans": 1722,
  "total_amount": 57671.0,
  "pct_loans_under_100k": 93.9605,
  "pct_loans_100k_250k": 3.6005,
  "pct_loans_250k_1m": 2.439,
  "pct_loans_sb_under_1m": 55.4007,
  "pct_amount_under_100k": 42.2275,
  "pct_amount_100k_250k": 18.3836,
  "pct_amount_250k_1m": 39.3889,
  "pct_amount_sb_under_1m": 45.5498,
  "pct_loans_lmi_tract": 0.0,
  "pct_amount_lmi_tract": 0.0,
  "pct_loans_low_income": 0.0,
  "pct_loans_moderate_income": 0.0,
  "pct_loans_middle_upper_income": 100.0,
  "pct_amount_low_income": 0.0,
  "pct_amount_moderate_income": 0.0,
  "pct_amount_middle_upper_income": 100.0,
  "num_under_100k": 1618,
  "num_100k_250k": 62,
  "num_250k_1m": 42,
  "amt_under_100k": 24353.0,
  "amt_100k_250k": 10602.0,
  "amt_250k_1m": 22716.0,
  "numsb_under_1m": 954,
  "amtsb_under_1m": 26269.0,
  "lmi_tract_loans": 0,
  "lmi_tract_amount": 0.0,
  "low_income_loans": 0,
  "moderate_income_loans": 0,
  "midu_income_loans": 1683,
  "low_income_amount": 0.0,
  "moderate_income_amount": 0.0,
  "midu_income_amount": 57378.0,
  "unknown_income_loans": 39,
  "unknown_income_amount": 293.0,
  "cbsa_code": "28620",
  "cbsa_name": "Kill Devil Hills, NC"
}