{
  "year": 2024,
  "total_loans": 10216,
  "total_amount": 368127.0,
  "pct_loans_under_100k": 93.5689,
  "pct_loans_100k_250k": 3.4945,
  "pct_loans_250k_1m": 2.9366,
  "pct_loans_sb_under_1m": 54.0623,
  "pct_amount_under_100k": 41.0426,
  "pct_amount_100k_250k": 16.349,
  "pct_amount_250k_1m": 42.6084,
  "pct_amount_sb_under_1m": 36.4885,
  "pct_loans_lmi_tract": 26.3635,
  "pct_amount_lmi_tract": 33.776,
  "pct_loans_low_income": 3.3435,
  "pct_loans_moderate_income": 23.02,
  "pct_loans_middle_upper_income": 73.6365,
  "pct_amount_low_income": 4.7623,
  "pct_amount_moderate_income": 29.0137,
  "pct_amount_middle_upper_income": 66.224,
  "num_under_100k": 9559,
  "num_100k_250k": 357,
  "num_250k_1m": 300,
  "amt_under_100k": 151089.0,
  "amt_100k_250k": 60185.0,
  "amt_250k_1m": 156853.0,
  "numsb_under_1m": 5523,
  "amtsb_under_1m": 134324.0,
  "lmi_tract_loans": 2673,
  "lmi_tract_amount": 124009.0,
  "low_income_loans": 339,
  "moderate_income_loans": 2334,
  "midu_income_loans": 7466,
  "low_income_amount": 17485.0,
  "moderate_income_amount": 106524.0,
  "midu_income_amount": 243142.0,
  "unknown_income_loans": 77,
  "unknown_income_amount": 976.0,
  "cbsa_code": "48900",
  "cbsa_name": "Wilmington, NC"
}